lib_code/__init__.py
lib_code/edit_imports.py
lib_code/log_step.py
lib_code/map_module.py
lib_code/parse_imports.py
lib_compute/__init__.py
lib_compute/deserialization.py
lib_compute/graph_alg.py
lib_compute/map_rdx.py
lib_compute/partitioning.py
lib_compute/scrape_utils.py
lib_compute/serialization.py
lib_compute/typon_math.py
lib_compute/M3/__init__.py
lib_compute/M3/m3.py
lib_dsa/__init__.py
lib_dsa/byte_array.py
lib_dsa/byte_array_st.py
lib_dsa/graph_db.py
lib_dsa/kv_db.py
lib_dsa/kv_iter.py
lib_dsa/mem_structs.py
lib_dsa/segmented_reader.py
lib_py_parse/__api__.py
lib_py_parse/__init__.py
lib_py_parse/helper/__init__.py
lib_py_parse/helper/eval_helper.py
lib_py_parse/helper/eval_service.py
lib_py_parse/helper/type_resolver.py
lib_py_parse/parse/__init__.py
lib_py_parse/parse/parse_L0_skeleton.py
lib_py_parse/parse/parse_skeleton.py
lib_py_parse/parse/parser.py
lib_py_parse/parse/rm_comments.py
lib_py_parse/utils/__init__.py
lib_py_parse/utils/constants.py
lib_py_parse/utils/exceptions.py
lib_py_parse/utils/fmt_utils.py
lib_py_parse/utils/fs_mod.py
lib_py_parse/utils/parsing_utils.py
libSDT8-0.0.1.dist-info/METADATA
libSDT8-0.0.1.dist-info/WHEEL
libSDT8-0.0.1.dist-info/top_level.txt
libSDT8-0.0.1.dist-info/RECORD
