Metadata-Version: 2.1
Name: libSDT8
Version: 0.0.1
Summary: Local packages for development
Home-page: http://pypi.python.org/pypi/libSDT8/0.0.1
Author: hypothesisbase
Author-email: support@hypothesisbase.com
License: MIT
Requires-Dist: bs4
Requires-Dist: leveldb
Requires-Dist: selenium
Requires-Dist: requests
Requires-Dist: pandas
